{
	"neuron_params": {
		"tau_m": 8.0,
		"tau_refrac": 1.0,
		"v_rest": -60.0,
		"v_thresh": -55.0,
		"v_reset": -70.0,
		"e_rev_I": -100.0
	},
	"neuron_params_inhib": {
		"tau_m": 12.0,
		"tau_refrac": 1.0,
		"v_rest": -70.0,
		"v_thresh": -60.0,
		"v_reset": -75.0,
		"e_rev_I": -100.0
	},
	"population": {
		"number" : 3,
		"weight_exh" : 0.013,
		"weight_exh_self" : 0.001,
		"weight_inh" : -0.060,
		"inhib_number" : 1,
		"self_exc_number" : 1
	},
	"noise": {
		"number" : 2,
		"weight_rand" : 0.004,
		"probability": 1.0,
		"noise_rate" : 80.0
	},
	"trigger": {
		"weight" : 0.015
	},	
	"start" : 0.0,	
	"duration" : 30000.0,
	"bin_size" : 30
}

